bitcore/__init__.py
bitcore/checks.py
bitcore/core.py
bitcorex-0.1.0.dist-info/licenses/LICENSE
bitcorex-0.1.0.dist-info/METADATA
bitcorex-0.1.0.dist-info/WHEEL
bitcorex-0.1.0.dist-info/top_level.txt
bitcorex-0.1.0.dist-info/RECORD
