Metadata-Version: 2.4
Name: bitcorex
Version: 0.1.0
Summary: Bitwise operations library for Python
Author-email: Odiljonov Boburmirzo <odiljonovboburmirzo17@gmail.com>
Requires-Python: >=3.7
License-File: LICENSE
Dynamic: license-file
